{
  "updated_label": "2026.06.01 20:07",
  "trade_date": "2026.06.01",
  "market_basis": "통합(KRX+NXT)",
  "stock": {
    "name": "삼성전자",
    "ticker": "005930",
    "market": "KOSPI",
    "close": 355000,
    "change": 36500,
    "change_pct": 11.46,
    "open": 318000,
    "high": 355500,
    "low": 311000,
    "volume": 81557705,
    "marketcap": 2040351234192000
  },
  "investors_hist": [
    {
      "date": "06.01",
      "markets": {
        "UN": {
          "value": {
            "개인": -15805,
            "외국인": 3585,
            "기관": 14371,
            "금융투자": 13813,
            "투신": 885,
            "사모": -461,
            "연기금": 1072,
            "보험": -845,
            "은행": -39
          },
          "volume": {
            "개인": -4620986,
            "외국인": 996165,
            "기관": 4267090,
            "금융투자": 4051793,
            "투신": 253060,
            "사모": -123826,
            "연기금": 355946,
            "보험": -242673,
            "은행": -11797
          }
        },
        "J": {
          "value": {
            "개인": -10876,
            "외국인": -415,
            "기관": 12899,
            "금융투자": 12836,
            "투신": 695,
            "사모": -783,
            "연기금": 1083,
            "보험": -843,
            "은행": -39
          },
          "volume": {
            "개인": -3173072,
            "외국인": -180865,
            "기관": 3832695,
            "금융투자": 3765007,
            "투신": 198542,
            "사모": -221952,
            "연기금": 359061,
            "보험": -242073,
            "은행": -11797
          }
        },
        "NX": {
          "value": {
            "개인": -4929,
            "외국인": 4001,
            "기관": 1472,
            "금융투자": 978,
            "투신": 190,
            "사모": 322,
            "연기금": -11,
            "보험": -2,
            "은행": 0
          },
          "volume": {
            "개인": -1447914,
            "외국인": 1177030,
            "기관": 434395,
            "금융투자": 286786,
            "투신": 54518,
            "사모": 98126,
            "연기금": -3115,
            "보험": -600,
            "은행": 0
          }
        }
      }
    },
    {
      "date": "05.29",
      "markets": {
        "UN": {
          "value": {
            "개인": -16943,
            "외국인": -1515,
            "기관": 18004,
            "금융투자": 13174,
            "투신": 2794,
            "사모": 1684,
            "연기금": 354,
            "보험": 0,
            "은행": 2
          },
          "volume": {
            "개인": -5381325,
            "외국인": -509411,
            "기관": 5745512,
            "금융투자": 4209196,
            "투신": 883023,
            "사모": 538880,
            "연기금": 116048,
            "보험": -732,
            "은행": 420
          }
        },
        "J": {
          "value": {
            "개인": -13341,
            "외국인": -3278,
            "기관": 16666,
            "금융투자": 12102,
            "투신": 2791,
            "사모": 1434,
            "연기금": 354,
            "보험": -1,
            "은행": 2
          },
          "volume": {
            "개인": -4237361,
            "외국인": -1061741,
            "기관": 5314304,
            "금융투자": 3864197,
            "투신": 882048,
            "사모": 457529,
            "연기금": 116047,
            "보험": -805,
            "은행": 420
          }
        },
        "NX": {
          "value": {
            "개인": -3602,
            "외국인": 1762,
            "기관": 1338,
            "금융투자": 1073,
            "투신": 3,
            "사모": 250,
            "연기금": 0,
            "보험": 0,
            "은행": 0
          },
          "volume": {
            "개인": -1143964,
            "외국인": 552330,
            "기관": 431208,
            "금융투자": 344999,
            "투신": 975,
            "사모": 81351,
            "연기금": 1,
            "보험": 73,
            "은행": 0
          }
        }
      }
    },
    {
      "date": "05.28",
      "markets": {
        "UN": {
          "value": {
            "개인": 24098,
            "외국인": -18249,
            "기관": -6370,
            "금융투자": -6726,
            "투신": -423,
            "사모": 555,
            "연기금": 192,
            "보험": 91,
            "은행": -33
          },
          "volume": {
            "개인": 8074696,
            "외국인": -6084939,
            "기관": -2166041,
            "금융투자": -2285715,
            "투신": -141622,
            "사모": 184285,
            "연기금": 66547,
            "보험": 30737,
            "은행": -11358
          }
        },
        "J": {
          "value": {
            "개인": 19378,
            "외국인": -15501,
            "기관": -4731,
            "금융투자": -5038,
            "투신": -423,
            "사모": 508,
            "연기금": 192,
            "보험": 92,
            "은행": -33
          },
          "volume": {
            "개인": 6500347,
            "외국인": -5173125,
            "기관": -1613562,
            "금융투자": -1717062,
            "투신": -141620,
            "사모": 169034,
            "연기금": 66647,
            "보험": 30937,
            "은행": -11358
          }
        },
        "NX": {
          "value": {
            "개인": 4720,
            "외국인": -2749,
            "기관": -1639,
            "금융투자": -1688,
            "투신": 0,
            "사모": 47,
            "연기금": 0,
            "보험": -1,
            "은행": 0
          },
          "volume": {
            "개인": 1574349,
            "외국인": -911814,
            "기관": -552479,
            "금융투자": -568653,
            "투신": -2,
            "사모": 15251,
            "연기금": -100,
            "보험": -200,
            "은행": 0
          }
        }
      }
    },
    {
      "date": "05.27",
      "markets": {
        "UN": {
          "value": {
            "개인": -8087,
            "외국인": 3675,
            "기관": 6173,
            "금융투자": 4716,
            "투신": -112,
            "사모": 2852,
            "연기금": -449,
            "보험": -702,
            "은행": -51
          },
          "volume": {
            "개인": -2500402,
            "외국인": 1138816,
            "기관": 1915951,
            "금융투자": 1458426,
            "투신": -30798,
            "사모": 899085,
            "연기금": -145234,
            "보험": -223833,
            "은행": -16352
          }
        },
        "J": {
          "value": {
            "개인": -3601,
            "외국인": -809,
            "기관": 4953,
            "금융투자": 4584,
            "투신": 163,
            "사모": 1469,
            "연기금": -447,
            "보험": -694,
            "은행": -51
          },
          "volume": {
            "개인": -1105685,
            "외국인": -274173,
            "기관": 1550904,
            "금융투자": 1430609,
            "투신": 58359,
            "사모": 466642,
            "연기금": -144568,
            "보험": -221374,
            "은행": -16352
          }
        },
        "NX": {
          "value": {
            "개인": -4486,
            "외국인": 4484,
            "기관": 1221,
            "금융투자": 131,
            "투신": -275,
            "사모": 1383,
            "연기금": -2,
            "보험": -8,
            "은행": 0
          },
          "volume": {
            "개인": -1394717,
            "외국인": 1412989,
            "기관": 365047,
            "금융투자": 27817,
            "투신": -89157,
            "사모": 432443,
            "연기금": -666,
            "보험": -2459,
            "은행": 0
          }
        }
      }
    },
    {
      "date": "05.26",
      "markets": {
        "UN": {
          "value": {
            "개인": -13688,
            "외국인": 7674,
            "기관": 6513,
            "금융투자": 1045,
            "투신": 5181,
            "사모": 721,
            "연기금": 256,
            "보험": -465,
            "은행": -174
          },
          "volume": {
            "개인": -4549651,
            "외국인": 2548451,
            "기관": 2167651,
            "금융투자": 326361,
            "투신": 1742988,
            "사모": 242490,
            "연기금": 85641,
            "보험": -155063,
            "은행": -57887
          }
        },
        "J": {
          "value": {
            "개인": -9828,
            "외국인": 5706,
            "기관": 4549,
            "금융투자": -899,
            "투신": 5183,
            "사모": 696,
            "연기금": 256,
            "보험": -465,
            "은행": -174
          },
          "volume": {
            "개인": -3263161,
            "외국인": 1891734,
            "기관": 1513469,
            "금융투자": -321199,
            "투신": 1743545,
            "사모": 234218,
            "연기금": 85643,
            "보험": -155063,
            "은행": -57887
          }
        },
        "NX": {
          "value": {
            "개인": -3860,
            "외국인": 1968,
            "기관": 1964,
            "금융투자": 1944,
            "투신": -2,
            "사모": 25,
            "연기금": 0,
            "보험": 0,
            "은행": 0
          },
          "volume": {
            "개인": -1286490,
            "외국인": 656717,
            "기관": 654182,
            "금융투자": 647560,
            "투신": -557,
            "사모": 8272,
            "연기금": -2,
            "보험": 0,
            "은행": 0
          }
        }
      }
    },
    {
      "date": "05.22",
      "markets": {
        "UN": {
          "value": {
            "개인": 13532,
            "외국인": -12826,
            "기관": -1314,
            "금융투자": 394,
            "투신": 323,
            "사모": -1569,
            "연기금": -211,
            "보험": -229,
            "은행": -4
          },
          "volume": {
            "개인": 4602146,
            "외국인": -4354342,
            "기관": -454737,
            "금융투자": 129912,
            "투신": 109862,
            "사모": -534113,
            "연기금": -74884,
            "보험": -78141,
            "은행": -1490
          }
        },
        "J": {
          "value": {
            "개인": 10604,
            "외국인": -10075,
            "기관": -893,
            "금융투자": 693,
            "투신": 336,
            "사모": -1496,
            "연기금": -176,
            "보험": -229,
            "은행": -4
          },
          "volume": {
            "개인": 3602972,
            "외국인": -3419695,
            "기관": -307631,
            "금융투자": 235756,
            "투신": 114181,
            "사모": -509617,
            "연기금": -63037,
            "보험": -78141,
            "은행": -1490
          }
        },
        "NX": {
          "value": {
            "개인": 2928,
            "외국인": -2751,
            "기관": -421,
            "금융투자": -299,
            "투신": -13,
            "사모": -73,
            "연기금": -35,
            "보험": 0,
            "은행": 0
          },
          "volume": {
            "개인": 999174,
            "외국인": -934647,
            "기관": -147106,
            "금융투자": -105844,
            "투신": -4319,
            "사모": -24496,
            "연기금": -11847,
            "보험": 0,
            "은행": 0
          }
        }
      }
    },
    {
      "date": "05.21",
      "markets": {
        "UN": {
          "value": {
            "개인": -18326,
            "외국인": 11186,
            "기관": 8377,
            "금융투자": 8694,
            "투신": 737,
            "사모": -269,
            "연기금": -361,
            "보험": -317,
            "은행": 13
          },
          "volume": {
            "개인": -6157932,
            "외국인": 3751502,
            "기관": 2825869,
            "금융투자": 2934557,
            "투신": 245858,
            "사모": -93728,
            "연기금": -118283,
            "보험": -106809,
            "은행": 4752
          }
        },
        "J": {
          "value": {
            "개인": -17654,
            "외국인": 10954,
            "기관": 7729,
            "금융투자": 7873,
            "투신": 746,
            "사모": -110,
            "연기금": -361,
            "보험": -317,
            "은행": 13
          },
          "volume": {
            "개인": -5931378,
            "외국인": 3672423,
            "기관": 2608486,
            "금융투자": 2656881,
            "투신": 248937,
            "사모": -38282,
            "연기금": -118301,
            "보험": -106748,
            "은행": 4752
          }
        },
        "NX": {
          "value": {
            "개인": -672,
            "외국인": 232,
            "기관": 648,
            "금융투자": 821,
            "투신": -9,
            "사모": -159,
            "연기금": 0,
            "보험": 0,
            "은행": 0
          },
          "volume": {
            "개인": -226554,
            "외국인": 79079,
            "기관": 217383,
            "금융투자": 277676,
            "투신": -3079,
            "사모": -55446,
            "연기금": 18,
            "보험": -61,
            "은행": 0
          }
        }
      }
    },
    {
      "date": "05.20",
      "markets": {
        "UN": {
          "value": {
            "개인": 4337,
            "외국인": -14872,
            "기관": 9340,
            "금융투자": 6821,
            "투신": 717,
            "사모": 1539,
            "연기금": 102,
            "보험": 107,
            "은행": 55
          },
          "volume": {
            "개인": 1544467,
            "외국인": -5390876,
            "기관": 3416765,
            "금융투자": 2487017,
            "투신": 264602,
            "사모": 567628,
            "연기금": 37561,
            "보험": 39240,
            "은행": 20358
          }
        },
        "J": {
          "value": {
            "개인": 7672,
            "외국인": -15796,
            "기관": 7535,
            "금융투자": 5135,
            "투신": 713,
            "사모": 1418,
            "연기금": 100,
            "보험": 112,
            "은행": 55
          },
          "volume": {
            "개인": 2765915,
            "외국인": -5733354,
            "기관": 2756787,
            "금융투자": 1870444,
            "투신": 263064,
            "사모": 523783,
            "연기금": 36805,
            "보험": 40974,
            "은행": 20358
          }
        },
        "NX": {
          "value": {
            "개인": -3335,
            "외국인": 924,
            "기관": 1805,
            "금융투자": 1686,
            "투신": 4,
            "사모": 121,
            "연기금": 2,
            "보험": -5,
            "은행": 0
          },
          "volume": {
            "개인": -1221448,
            "외국인": 342478,
            "기관": 659978,
            "금융투자": 616573,
            "투신": 1538,
            "사모": 43845,
            "연기금": 756,
            "보험": -1734,
            "은행": 0
          }
        }
      }
    },
    {
      "date": "05.19",
      "markets": {
        "UN": {
          "value": {
            "개인": 24649,
            "외국인": -29308,
            "기관": 4400,
            "금융투자": 4233,
            "투신": -355,
            "사모": 432,
            "연기금": 109,
            "보험": -25,
            "은행": 11
          },
          "volume": {
            "개인": 9029141,
            "외국인": -10707356,
            "기관": 1584933,
            "금융투자": 1518250,
            "투신": -127749,
            "사모": 156373,
            "연기금": 44617,
            "보험": -8931,
            "은행": 4255
          }
        },
        "J": {
          "value": {
            "개인": 21341,
            "외국인": -25355,
            "기관": 3944,
            "금융투자": 3607,
            "투신": -355,
            "사모": 601,
            "연기금": 109,
            "보험": -25,
            "은행": 11
          },
          "volume": {
            "개인": 7818601,
            "외국인": -9263047,
            "기관": 1418906,
            "금융투자": 1290884,
            "투신": -127753,
            "사모": 217497,
            "연기금": 44561,
            "보험": -8931,
            "은행": 4255
          }
        },
        "NX": {
          "value": {
            "개인": 3308,
            "외국인": -3953,
            "기관": 456,
            "금융투자": 626,
            "투신": 0,
            "사모": -169,
            "연기금": 0,
            "보험": 0,
            "은행": 0
          },
          "volume": {
            "개인": 1210540,
            "외국인": -1444309,
            "기관": 166027,
            "금융투자": 227366,
            "투신": 4,
            "사모": -61124,
            "연기금": 56,
            "보험": 0,
            "은행": 0
          }
        }
      }
    },
    {
      "date": "05.18",
      "markets": {
        "UN": {
          "value": {
            "개인": 4029,
            "외국인": -12321,
            "기관": 8304,
            "금융투자": 7014,
            "투신": 664,
            "사모": 387,
            "연기금": 353,
            "보험": -10,
            "은행": -82
          },
          "volume": {
            "개인": 1480510,
            "외국인": -4433275,
            "기관": 2959035,
            "금융투자": 2477942,
            "투신": 240637,
            "사모": 142357,
            "연기금": 138726,
            "보험": -3461,
            "은행": -29163
          }
        },
        "J": {
          "value": {
            "개인": 4584,
            "외국인": -12415,
            "기관": 7860,
            "금융투자": 6351,
            "투신": 705,
            "사모": 557,
            "연기금": 356,
            "보험": -10,
            "은행": -82
          },
          "volume": {
            "개인": 1689597,
            "외국인": -4486093,
            "기관": 2803397,
            "금융투자": 2241796,
            "투신": 255329,
            "사모": 205239,
            "연기금": 139601,
            "보험": -3461,
            "은행": -29163
          }
        },
        "NX": {
          "value": {
            "개인": -555,
            "외국인": 94,
            "기관": 445,
            "금융투자": 663,
            "투신": -41,
            "사모": -169,
            "연기금": -2,
            "보험": 0,
            "은행": 0
          },
          "volume": {
            "개인": -209087,
            "외국인": 52818,
            "기관": 155638,
            "금융투자": 236146,
            "투신": -14692,
            "사모": -62882,
            "연기금": -875,
            "보험": 0,
            "은행": 0
          }
        }
      }
    }
  ],
  "short_latest": {
    "date": "2026.05.28",
    "qty": 0,
    "ratio": 0.0,
    "qty_change": 0,
    "qty_change_pct": 0.0
  },
  "short_trend": [
    {
      "date": "05.14",
      "qty": 316122,
      "ratio": 0.01
    },
    {
      "date": "05.15",
      "qty": 243518,
      "ratio": 0.0
    },
    {
      "date": "05.18",
      "qty": 221813,
      "ratio": 0.0
    },
    {
      "date": "05.19",
      "qty": 179226,
      "ratio": 0.0
    },
    {
      "date": "05.20",
      "qty": 94881,
      "ratio": 0.0
    },
    {
      "date": "05.21",
      "qty": 0,
      "ratio": 0.0
    },
    {
      "date": "05.22",
      "qty": 0,
      "ratio": 0.0
    },
    {
      "date": "05.26",
      "qty": 0,
      "ratio": 0.0
    },
    {
      "date": "05.27",
      "qty": 0,
      "ratio": 0.0
    },
    {
      "date": "05.28",
      "qty": 0,
      "ratio": 0.0
    }
  ],
  "short_pending": false,
  "opinions": [
    {
      "date": "05.28",
      "date_full": "20260528",
      "broker": "KB",
      "opinion": "BUY",
      "prev_opinion": "BUY",
      "goal_price": 530000,
      "dprt": "-42.08"
    },
    {
      "date": "05.27",
      "date_full": "20260527",
      "broker": "미래에셋",
      "opinion": "매수",
      "prev_opinion": "매수",
      "goal_price": 550000,
      "dprt": "-45.64"
    },
    {
      "date": "05.22",
      "date_full": "20260522",
      "broker": "NH투자",
      "opinion": "BUY",
      "prev_opinion": "BUY",
      "goal_price": 490000,
      "dprt": "-38.88"
    },
    {
      "date": "05.21",
      "date_full": "20260521",
      "broker": "유안타",
      "opinion": "BUY",
      "prev_opinion": "BUY",
      "goal_price": 390000,
      "dprt": "-29.23"
    },
    {
      "date": "05.21",
      "date_full": "20260521",
      "broker": "신한투자증권",
      "opinion": "매수",
      "prev_opinion": "매수",
      "goal_price": 550000,
      "dprt": "-49.82"
    },
    {
      "date": "05.20",
      "date_full": "20260520",
      "broker": "한국투자",
      "opinion": "매수",
      "prev_opinion": "매수",
      "goal_price": 570000,
      "dprt": "-51.67"
    },
    {
      "date": "05.19",
      "date_full": "20260519",
      "broker": "다올투자",
      "opinion": "BUY",
      "prev_opinion": "BUY",
      "goal_price": 450000,
      "dprt": "-37.56"
    },
    {
      "date": "05.18",
      "date_full": "20260518",
      "broker": "IM증권",
      "opinion": "BUY",
      "prev_opinion": "BUY",
      "goal_price": 400000,
      "dprt": "-32.38"
    },
    {
      "date": "05.18",
      "date_full": "20260518",
      "broker": "유진투자",
      "opinion": "Strong BUY",
      "prev_opinion": "Strong BUY",
      "goal_price": 500000,
      "dprt": "-45.90"
    },
    {
      "date": "05.15",
      "date_full": "20260515",
      "broker": "하나증권",
      "opinion": "BUY",
      "prev_opinion": "BUY",
      "goal_price": 430000,
      "dprt": "-31.16"
    },
    {
      "date": "05.13",
      "date_full": "20260513",
      "broker": "현대차",
      "opinion": "BUY",
      "prev_opinion": "BUY",
      "goal_price": 340000,
      "dprt": "-17.94"
    },
    {
      "date": "05.11",
      "date_full": "20260511",
      "broker": "LS증권",
      "opinion": "Buy",
      "prev_opinion": "Buy",
      "goal_price": 320000,
      "dprt": "-16.09"
    },
    {
      "date": "05.11",
      "date_full": "20260511",
      "broker": "키움",
      "opinion": "BUY",
      "prev_opinion": "BUY",
      "goal_price": 330000,
      "dprt": "-18.64"
    },
    {
      "date": "05.11",
      "date_full": "20260511",
      "broker": "대신",
      "opinion": "BUY",
      "prev_opinion": "BUY",
      "goal_price": 450000,
      "dprt": "-40.33"
    },
    {
      "date": "05.07",
      "date_full": "20260507",
      "broker": "SK",
      "opinion": "매수",
      "prev_opinion": "매수",
      "goal_price": 500000,
      "dprt": "-46.80"
    },
    {
      "date": "05.06",
      "date_full": "20260506",
      "broker": "교보",
      "opinion": "BUY",
      "prev_opinion": "BUY",
      "goal_price": 330000,
      "dprt": "-29.55"
    },
    {
      "date": "05.04",
      "date_full": "20260504",
      "broker": "DB증권",
      "opinion": "BUY",
      "prev_opinion": "BUY",
      "goal_price": 280000,
      "dprt": "-21.25"
    },
    {
      "date": "05.04",
      "date_full": "20260504",
      "broker": "삼성",
      "opinion": "BUY",
      "prev_opinion": "BUY",
      "goal_price": 300000,
      "dprt": "-26.50"
    },
    {
      "date": "05.04",
      "date_full": "20260504",
      "broker": "한화투자",
      "opinion": "BUY",
      "prev_opinion": "BUY",
      "goal_price": 330000,
      "dprt": "-33.18"
    }
  ],
  "target_consensus": {
    "avg": 423158,
    "high": 570000,
    "low": 280000,
    "count": 19,
    "days": 30
  },
  "signals": [
    {
      "kind": "warn",
      "text": "장중 변동폭 확대 14.0%"
    },
    {
      "kind": "pos",
      "text": "고가권 마감 — 매수 우위(짧은 윗꼬리)"
    },
    {
      "kind": "pos",
      "text": "최근 20일 신고가"
    },
    {
      "kind": "pos",
      "text": "외국인·기관 동반 순매수 (+3585억/+14371억)"
    }
  ]
}