{
  "updated_label": "2026.06.05 03:16",
  "trade_date": "2026.06.04",
  "market_basis": "통합(KRX+NXT)",
  "stock": {
    "name": "네이버",
    "ticker": "035420",
    "market": "KOSPI",
    "close_by_market": {
      "UN": 267500,
      "J": 267500,
      "NX": 254000
    },
    "prev_krx_close": 280500,
    "after_nxt_close": false,
    "open": 267500,
    "high": 275000,
    "low": 255000,
    "volume": 8762642,
    "marketcap": 41963735080000
  },
  "investors_hist": [
    {
      "date": "06.04",
      "markets": {
        "UN": {
          "value": {
            "개인": 934,
            "외국인": -1517,
            "기관": 333,
            "금융투자": 520,
            "투신": -150,
            "사모": -121,
            "연기금": 59,
            "보험": -8,
            "은행": 0
          },
          "volume": {
            "개인": 358708,
            "외국인": -579302,
            "기관": 123857,
            "금융투자": 195679,
            "투신": -56615,
            "사모": -46937,
            "연기금": 22258,
            "보험": -3282,
            "은행": -149
          }
        },
        "J": {
          "value": {
            "개인": 908,
            "외국인": -1255,
            "기관": 321,
            "금융투자": 491,
            "투신": -150,
            "사모": -97,
            "연기금": 59,
            "보험": -8,
            "은행": 0
          },
          "volume": {
            "개인": 350165,
            "외국인": -480144,
            "기관": 119070,
            "금융투자": 184762,
            "투신": -56615,
            "사모": -37807,
            "연기금": 22258,
            "보험": -3282,
            "은행": -149
          }
        },
        "NX": {
          "value": {
            "개인": 27,
            "외국인": -262,
            "기관": 13,
            "금융투자": 29,
            "투신": 0,
            "사모": -24,
            "연기금": 0,
            "보험": 0,
            "은행": 0
          },
          "volume": {
            "개인": 8543,
            "외국인": -99158,
            "기관": 4787,
            "금융투자": 10917,
            "투신": 0,
            "사모": -9130,
            "연기금": 0,
            "보험": 0,
            "은행": 0
          }
        }
      }
    },
    {
      "date": "06.02",
      "markets": {
        "UN": {
          "value": {
            "개인": 4218,
            "외국인": -4598,
            "기관": 347,
            "금융투자": -253,
            "투신": 56,
            "사모": 112,
            "연기금": 329,
            "보험": 59,
            "은행": -1
          },
          "volume": {
            "개인": 1561197,
            "외국인": -1696631,
            "기관": 120716,
            "금융투자": -93393,
            "투신": 18471,
            "사모": 37349,
            "연기금": 120484,
            "보험": 21204,
            "은행": -231
          }
        },
        "J": {
          "value": {
            "개인": 3584,
            "외국인": -4080,
            "기관": 333,
            "금융투자": -271,
            "투신": 56,
            "사모": 124,
            "연기금": 324,
            "보험": 55,
            "은행": -1
          },
          "volume": {
            "개인": 1341130,
            "외국인": -1517727,
            "기관": 115597,
            "금융투자": -100004,
            "투신": 18749,
            "사모": 41496,
            "연기금": 119034,
            "보험": 19721,
            "은행": -231
          }
        },
        "NX": {
          "value": {
            "개인": 633,
            "외국인": -518,
            "기관": 13,
            "금융투자": 18,
            "투신": -1,
            "사모": -12,
            "연기금": 4,
            "보험": 4,
            "은행": 0
          },
          "volume": {
            "개인": 220067,
            "외국인": -178904,
            "기관": 5119,
            "금융투자": 6611,
            "투신": -278,
            "사모": -4147,
            "연기금": 1450,
            "보험": 1483,
            "은행": 0
          }
        }
      }
    },
    {
      "date": "06.01",
      "markets": {
        "UN": {
          "value": {
            "개인": 3121,
            "외국인": -4382,
            "기관": 1536,
            "금융투자": -951,
            "투신": 578,
            "사모": 597,
            "연기금": 1097,
            "보험": 217,
            "은행": 1
          },
          "volume": {
            "개인": 1174494,
            "외국인": -1626762,
            "기관": 549152,
            "금융투자": -356429,
            "투신": 209356,
            "사모": 213754,
            "연기금": 401817,
            "보험": 80881,
            "은행": 545
          }
        },
        "J": {
          "value": {
            "개인": 1496,
            "외국인": -3071,
            "기관": 1760,
            "금융투자": -706,
            "투신": 578,
            "사모": 573,
            "연기금": 1098,
            "보험": 218,
            "은행": 1
          },
          "volume": {
            "개인": 567534,
            "외국인": -1135272,
            "기관": 633251,
            "금융투자": -263106,
            "투신": 209356,
            "사모": 204024,
            "연기금": 401847,
            "보험": 81367,
            "은행": 545
          }
        },
        "NX": {
          "value": {
            "개인": 1625,
            "외국인": -1311,
            "기관": -224,
            "금융투자": -246,
            "투신": 0,
            "사모": 24,
            "연기금": -1,
            "보험": -1,
            "은행": 0
          },
          "volume": {
            "개인": 606960,
            "외국인": -491490,
            "기관": -84099,
            "금융투자": -93323,
            "투신": 0,
            "사모": 9730,
            "연기금": -30,
            "보험": -486,
            "은행": 0
          }
        }
      }
    },
    {
      "date": "05.29",
      "markets": {
        "UN": {
          "value": {
            "개인": -3225,
            "외국인": 923,
            "기관": 2248,
            "금융투자": 938,
            "투신": 440,
            "사모": 180,
            "연기금": 591,
            "보험": 95,
            "은행": 2
          },
          "volume": {
            "개인": -1430066,
            "외국인": 445940,
            "기관": 960578,
            "금융투자": 400856,
            "투신": 187051,
            "사모": 77142,
            "연기금": 253482,
            "보험": 40504,
            "은행": 817
          }
        },
        "J": {
          "value": {
            "개인": -2410,
            "외국인": 304,
            "기관": 2052,
            "금융투자": 737,
            "투신": 440,
            "사모": 187,
            "연기금": 591,
            "보험": 95,
            "은행": 2
          },
          "volume": {
            "개인": -1061647,
            "외국인": 161395,
            "기관": 877348,
            "금융투자": 314400,
            "투신": 187051,
            "사모": 80867,
            "연기금": 253482,
            "보험": 40504,
            "은행": 817
          }
        },
        "NX": {
          "value": {
            "개인": -815,
            "외국인": 619,
            "기관": 195,
            "금융투자": 202,
            "투신": 0,
            "사모": -8,
            "연기금": 0,
            "보험": 0,
            "은행": 0
          },
          "volume": {
            "개인": -368419,
            "외국인": 284545,
            "기관": 83230,
            "금융투자": 86456,
            "투신": 0,
            "사모": -3725,
            "연기금": 0,
            "보험": 0,
            "은행": 0
          }
        }
      }
    },
    {
      "date": "05.28",
      "markets": {
        "UN": {
          "value": {
            "개인": 98,
            "외국인": -288,
            "기관": 184,
            "금융투자": -104,
            "투신": 72,
            "사모": 52,
            "연기금": 132,
            "보험": 28,
            "은행": 0
          },
          "volume": {
            "개인": 57451,
            "외국인": -147828,
            "기관": 88097,
            "금융투자": -52878,
            "투신": 34387,
            "사모": 25027,
            "연기금": 65363,
            "보험": 13994,
            "은행": -19
          }
        },
        "J": {
          "value": {
            "개인": 188,
            "외국인": -332,
            "기관": 184,
            "금융투자": -99,
            "투신": 72,
            "사모": 47,
            "연기금": 132,
            "보험": 28,
            "은행": 0
          },
          "volume": {
            "개인": 100610,
            "외국인": -168305,
            "기관": 88078,
            "금융투자": -50290,
            "투신": 34387,
            "사모": 22557,
            "연기금": 65363,
            "보험": 13994,
            "은행": -19
          }
        },
        "NX": {
          "value": {
            "개인": -91,
            "외국인": 44,
            "기관": 0,
            "금융투자": -5,
            "투신": 0,
            "사모": 5,
            "연기금": 0,
            "보험": 0,
            "은행": 0
          },
          "volume": {
            "개인": -43159,
            "외국인": 20477,
            "기관": 19,
            "금융투자": -2588,
            "투신": 0,
            "사모": 2470,
            "연기금": 0,
            "보험": 0,
            "은행": 0
          }
        }
      }
    },
    {
      "date": "05.27",
      "markets": {
        "UN": {
          "value": {
            "개인": 97,
            "외국인": 219,
            "기관": -243,
            "금융투자": -131,
            "투신": -24,
            "사모": -22,
            "연기금": -25,
            "보험": -35,
            "은행": 0
          },
          "volume": {
            "개인": 49027,
            "외국인": 109797,
            "기관": -122001,
            "금융투자": -65757,
            "투신": -11865,
            "사모": -11244,
            "연기금": -12672,
            "보험": -17761,
            "은행": 10
          }
        },
        "J": {
          "value": {
            "개인": 85,
            "외국인": 186,
            "기관": -241,
            "금융투자": -130,
            "투신": -24,
            "사모": -22,
            "연기금": -25,
            "보험": -35,
            "은행": 0
          },
          "volume": {
            "개인": 42956,
            "외국인": 93343,
            "기관": -121348,
            "금융투자": -65104,
            "투신": -11865,
            "사모": -11244,
            "연기금": -12672,
            "보험": -17761,
            "은행": 10
          }
        },
        "NX": {
          "value": {
            "개인": 12,
            "외국인": 33,
            "기관": -1,
            "금융투자": -1,
            "투신": 0,
            "사모": 0,
            "연기금": 0,
            "보험": 0,
            "은행": 0
          },
          "volume": {
            "개인": 6071,
            "외국인": 16454,
            "기관": -653,
            "금융투자": -653,
            "투신": 0,
            "사모": 0,
            "연기금": 0,
            "보험": 0,
            "은행": 0
          }
        }
      }
    },
    {
      "date": "05.26",
      "markets": {
        "UN": {
          "value": {
            "개인": 358,
            "외국인": -285,
            "기관": -99,
            "금융투자": 25,
            "투신": -43,
            "사모": -3,
            "연기금": -73,
            "보험": -13,
            "은행": 0
          },
          "volume": {
            "개인": 177745,
            "외국인": -140920,
            "기관": -49675,
            "금융투자": 12155,
            "투신": -21359,
            "사모": -1673,
            "연기금": -36615,
            "보험": -6513,
            "은행": 9
          }
        },
        "J": {
          "value": {
            "개인": 344,
            "외국인": -207,
            "기관": -119,
            "금융투자": 13,
            "투신": -43,
            "사모": -3,
            "연기금": -73,
            "보험": -13,
            "은행": 0
          },
          "volume": {
            "개인": 171000,
            "외국인": -102165,
            "기관": -59650,
            "금융투자": 6196,
            "투신": -21359,
            "사모": -1673,
            "연기금": -36602,
            "보험": -6513,
            "은행": 9
          }
        },
        "NX": {
          "value": {
            "개인": 14,
            "외국인": -79,
            "기관": 20,
            "금융투자": 12,
            "투신": 0,
            "사모": 0,
            "연기금": 0,
            "보험": 0,
            "은행": 0
          },
          "volume": {
            "개인": 6745,
            "외국인": -38755,
            "기관": 9975,
            "금융투자": 5959,
            "투신": 0,
            "사모": 0,
            "연기금": -13,
            "보험": 0,
            "은행": 0
          }
        }
      }
    },
    {
      "date": "05.22",
      "markets": {
        "UN": {
          "value": {
            "개인": -199,
            "외국인": -12,
            "기관": 108,
            "금융투자": 53,
            "투신": -76,
            "사모": 5,
            "연기금": 115,
            "보험": 13,
            "은행": -1
          },
          "volume": {
            "개인": -97527,
            "외국인": -6314,
            "기관": 53295,
            "금융투자": 26305,
            "투신": -37341,
            "사모": 2228,
            "연기금": 56434,
            "보험": 6237,
            "은행": -420
          }
        },
        "J": {
          "value": {
            "개인": -157,
            "외국인": -47,
            "기관": 112,
            "금융투자": 57,
            "투신": -76,
            "사모": 5,
            "연기금": 115,
            "보험": 13,
            "은행": -1
          },
          "volume": {
            "개인": -76737,
            "외국인": -23672,
            "기관": 55179,
            "금융투자": 28189,
            "투신": -37341,
            "사모": 2228,
            "연기금": 56434,
            "보험": 6237,
            "은행": -420
          }
        },
        "NX": {
          "value": {
            "개인": -42,
            "외국인": 36,
            "기관": -4,
            "금융투자": -4,
            "투신": 0,
            "사모": 0,
            "연기금": 0,
            "보험": 0,
            "은행": 0
          },
          "volume": {
            "개인": -20790,
            "외국인": 17358,
            "기관": -1884,
            "금융투자": -1884,
            "투신": 0,
            "사모": 0,
            "연기금": 0,
            "보험": 0,
            "은행": 0
          }
        }
      }
    },
    {
      "date": "05.21",
      "markets": {
        "UN": {
          "value": {
            "개인": -476,
            "외국인": 274,
            "기관": 266,
            "금융투자": 152,
            "투신": 20,
            "사모": -4,
            "연기금": 101,
            "보험": -6,
            "은행": 0
          },
          "volume": {
            "개인": -238676,
            "외국인": 138179,
            "기관": 133365,
            "금융투자": 76147,
            "투신": 9967,
            "사모": -2122,
            "연기금": 50862,
            "보험": -3090,
            "은행": 59
          }
        },
        "J": {
          "value": {
            "개인": -359,
            "외국인": 132,
            "기관": 261,
            "금융투자": 147,
            "투신": 20,
            "사모": -4,
            "연기금": 101,
            "보험": -6,
            "은행": 0
          },
          "volume": {
            "개인": -179663,
            "외국인": 66429,
            "기관": 131000,
            "금융투자": 73782,
            "투신": 9967,
            "사모": -2122,
            "연기금": 50862,
            "보험": -3090,
            "은행": 59
          }
        },
        "NX": {
          "value": {
            "개인": -117,
            "외국인": 142,
            "기관": 5,
            "금융투자": 5,
            "투신": 0,
            "사모": 0,
            "연기금": 0,
            "보험": 0,
            "은행": 0
          },
          "volume": {
            "개인": -59013,
            "외국인": 71750,
            "기관": 2365,
            "금융투자": 2365,
            "투신": 0,
            "사모": 0,
            "연기금": 0,
            "보험": 0,
            "은행": 0
          }
        }
      }
    },
    {
      "date": "05.20",
      "markets": {
        "UN": {
          "value": {
            "개인": 431,
            "외국인": -172,
            "기관": -197,
            "금융투자": -158,
            "투신": -9,
            "사모": -4,
            "연기금": -23,
            "보험": -3,
            "은행": 0
          },
          "volume": {
            "개인": 224425,
            "외국인": -89249,
            "기관": -102854,
            "금융투자": -82621,
            "투신": -4523,
            "사모": -2327,
            "연기금": -11835,
            "보험": -1574,
            "은행": 25
          }
        },
        "J": {
          "value": {
            "개인": 285,
            "외국인": -74,
            "기관": -181,
            "금융투자": -142,
            "투신": -9,
            "사모": -4,
            "연기금": -23,
            "보험": -3,
            "은행": 0
          },
          "volume": {
            "개인": 148486,
            "외국인": -38731,
            "기관": -94465,
            "금융투자": -74232,
            "투신": -4523,
            "사모": -2327,
            "연기금": -11835,
            "보험": -1574,
            "은행": 25
          }
        },
        "NX": {
          "value": {
            "개인": 146,
            "외국인": -98,
            "기관": -16,
            "금융투자": -16,
            "투신": 0,
            "사모": 0,
            "연기금": 0,
            "보험": 0,
            "은행": 0
          },
          "volume": {
            "개인": 75939,
            "외국인": -50518,
            "기관": -8389,
            "금융투자": -8389,
            "투신": 0,
            "사모": 0,
            "연기금": 0,
            "보험": 0,
            "은행": 0
          }
        }
      }
    }
  ],
  "short_latest": {
    "date": "2026.06.01",
    "qty": 816647,
    "ratio": 0.52,
    "qty_change": 238708,
    "qty_change_pct": 41.3
  },
  "short_trend": [
    {
      "date": "05.18",
      "qty": 472051,
      "ratio": 0.3
    },
    {
      "date": "05.19",
      "qty": 460482,
      "ratio": 0.29
    },
    {
      "date": "05.20",
      "qty": 507039,
      "ratio": 0.32
    },
    {
      "date": "05.21",
      "qty": 552069,
      "ratio": 0.35
    },
    {
      "date": "05.22",
      "qty": 558043,
      "ratio": 0.36
    },
    {
      "date": "05.26",
      "qty": 589422,
      "ratio": 0.38
    },
    {
      "date": "05.27",
      "qty": 596427,
      "ratio": 0.38
    },
    {
      "date": "05.28",
      "qty": 517015,
      "ratio": 0.33
    },
    {
      "date": "05.29",
      "qty": 577939,
      "ratio": 0.37
    },
    {
      "date": "06.01",
      "qty": 816647,
      "ratio": 0.52
    }
  ],
  "short_pending": true,
  "opinions": [
    {
      "date": "05.28",
      "date_full": "20260528",
      "broker": "키움",
      "opinion": "BUY",
      "prev_opinion": "BUY",
      "goal_price": 250000,
      "dprt": "-20.48"
    },
    {
      "date": "05.21",
      "date_full": "20260521",
      "broker": "KB",
      "opinion": "BUY",
      "prev_opinion": "BUY",
      "goal_price": 280000,
      "dprt": "-31.61"
    },
    {
      "date": "05.21",
      "date_full": "20260521",
      "broker": "미래에셋",
      "opinion": "매수",
      "prev_opinion": "매수",
      "goal_price": 280000,
      "dprt": "-31.61"
    }
  ],
  "target_consensus": {
    "avg": 270000,
    "high": 280000,
    "low": 250000,
    "count": 3,
    "days": 30
  }
}